[
    
    {
        "_id": "6168306f3f4ea527f4b737f0",
        "picture": "https://i.postimg.cc/15wZWh9W/breakfast1.png",
        "name": "Bagel & and cream cheese",
        "category": "breakfast",
        "description": "Hello, Frost Faulkner! You have 7 unread messages.",
        "price": "$6.99"
    },
    {
        "_id": "616859e92b3f4fbd3c0be99d",
        "picture": "https://i.postimg.cc/4dFbxjvC/dinner3.png",
        "name": "Pork Tenderloin with Quinoa Pilaf",
        "category": "dinner",
        "description": "Hello, Frost Faulkner! You have 7 unread messages.",
        "price": "$8.99"
    },
    {
        "_id": "6168306fa5efcedee12def82",
        "picture": "https://i.postimg.cc/KYvSv1tV/breakfast2.png",
        "name": "Breakfast Sandwich",
        "category": "breakfast",
        "description": "Hello, Frost Faulkner! You have 7 unread messages.",
        "price": "$9.99"
    },
    {
        "_id": "616859e9060b3ad21a05a459",
        "picture": "https://i.postimg.cc/W4byMxWf/lunch2.png",
        "name": "Full Breakfast Fried Egg Toast Brunch",
        "category": "lunch",
        "description": "Hello, Frost Faulkner! You have 7 unread messages.",
        "price": "$3.99"
    },
    {
        "_id": "6168306fb2eeba72ca44d978",
        "picture": "https://i.postimg.cc/L8SFwC5m/breakfast4.png",
        "name": "Eggs Benedict",
        "category": "breakfast",
        "description": "Hello, Frost Faulkner! You have 7 unread messages.",
        "price": "$8.99"
    },
    {
        "_id": "6168306f1a1de958ad06aec3",
        "picture": "https://i.postimg.cc/vZFND4wh/breakfast5.png",
        "name": "Toast Croissant Fried Egg",
        "category": "breakfast",
        "description": "Hello, Frost Faulkner! You have 7 unread messages.",
        "price": "$19.99"
    },
    {
        "_id": "616859e96ab11fcbcbc1c36f",
        "picture": "https://i.postimg.cc/qRNZFyds/lunch1.png",
        "name": "Full Breakfast Fried Egg Toast Brunch",
        "category": "lunch",
        "description": "Hello, Frost Faulkner! You have 7 unread messages.",
        "price": "$3.99"
    },
    {
        "_id": "616855b62f833d1cf1264c69",
        "picture": "https://i.postimg.cc/VsSwC02P/breakfast6.png",
        "name": "Full Breakfast Fried Egg Toast Brunch",
        "category": "breakfast",
        "description": "Hello, Frost Faulkner! You have 7 unread messages.",
        "price": "$3.99"
    },
    
    {
        "_id": "616859e90de889990d855371",
        "picture": "https://i.postimg.cc/Pq3RKK0f/lunch3.png",
        "name": "Full Breakfast Fried Egg Toast Brunch",
        "category": "lunch",
        "description": "Hello, Frost Faulkner! You have 7 unread messages.",
        "price": "$3.99"
    },
    {
        "_id": "616859e9b40a1f78dfde1f40",
        "picture": "https://i.postimg.cc/ydNyB7ZX/dinner1.png",
        "name": "Salmon With GrapeFruit and Lentil Salad",
        "category": "dinner",
        "description": "Hello, Frost Faulkner! You have 7 unread messages.",
        "price": "$5.99"
    },
    {
        "_id": "616859e9dcbcc7714dedfa77",
        "picture": "https://i.postimg.cc/RCnDQ7d9/lunch4.png",
        "name": "Full Breakfast Fried Egg Toast Brunch",
        "category": "lunch",
        "description": "Hello, Frost Faulkner! You have 7 unread messages.",
        "price": "$3.99"
    },
    {
        "_id": "616859e92b58654f27803e35",
        "picture": "https://i.postimg.cc/rmwfrWm6/lunch5.png",
        "name": "Full Breakfast Fried Egg Toast Brunch",
        "category": "lunch",
        "description": "Hello, Frost Faulkner! You have 7 unread messages.",
        "price": "$3.99"
    },
    {
        "_id": "616859e93422b4bd85590fc7",
        "picture": "https://i.postimg.cc/VsSwC02P/breakfast6.png",
        "name": "Full Breakfast Fried Egg Toast Brunch French fries with cheese",
        "category": "dinner",
        "description": "Hello, Frost Faulkner! You have 7 unread messages.",
        "price": "$3.99"
    },
    {
        "_id": "616859e9bfa58aceb4e51d6f",
        "picture": "https://i.postimg.cc/8kFqXQ12/lunch6.png",
        "name": "Full Breakfast Fried Egg Toast Brunch",
        "category": "lunch",
        "description": "Hello, Frost Faulkner! You have 7 unread messages.",
        "price": "$3.99"
    },
    {
        "_id": "6168306ff2ccc39508a954b5",
        "picture": "https://i.postimg.cc/mgSWsY1C/breakfast3.png",
        "name": "Baked Chicken",
        "category": "breakfast",
        "description": "Hello, Frost Faulkner! You have 7 unread messages.",
        "price": "$10.99"
    },
    {
        "_id": "616859e956c911a96261154a",
        "picture": "https://i.postimg.cc/VsSwC02P/breakfast6.png",
        "name": "Garlic butter baked salmon",
        "category": "dinner",
        "description": "Hello, Frost Faulkner! You have 7 unread messages.",
        "price": "$8.99"
    },
    {
        "_id": "616859e9c025cb55a1a23aeb",
        "picture": "https://i.postimg.cc/6q2V2zz8/dinner2.png",
        "name": "Lemony Salmon Piccata",
        "category": "dinner",
        "description": "Hello, Frost Faulkner! You have 7 unread messages.",
        "price": "$3.99"
    },
    {
        "_id": "616859e9be75f02a6b195a0a",
        "picture": "https://i.postimg.cc/VsSwC02P/breakfast6.png",
        "name": "Baked Chicken",
        "category": "dinner",
        "description": "Hello, Frost Faulkner! You have 7 unread messages.",
        "price": "$3.99"
    }
]